bonerator/__init__.py
bonerator/compile.py
bonerator/document.py
bonerator/utils.py
bonerator/content/__init__.py
bonerator/content/command.py
bonerator/content/content.py
bonerator/content/section.py
bonerator/environment/__init__.py
bonerator/environment/environment.py
bonerator/environment/figure.py
bonerator/environment/minipage.py
bonerator/environment/sequence.py
bonerator/environment/table.py
bonerator/environment/preview/__init__.py
bonerator/environment/preview/environment.py
bonerator/environment/preview/table.py
bonerator/extensions/__init__.py
bonerator/feature/__init__.py
bonerator/feature/btex_bonelate.py
bonerator/feature/latex3.py
bonerator/feature/matrix.py
Bonerator-0.1.1.dist-info/LICENSE
Bonerator-0.1.1.dist-info/METADATA
Bonerator-0.1.1.dist-info/WHEEL
Bonerator-0.1.1.dist-info/top_level.txt
Bonerator-0.1.1.dist-info/RECORD
