Metadata-Version: 2.1
Name: Bonerator
Version: 0.1.1
Summary: 
Home-page: https://github.com/zrr1999/bonerator
Author: 六个骨头
Author-email: 2742392377@qq.com
License: UNKNOWN
Platform: any
Classifier: Programming Language :: Python :: 3
Classifier: License :: OSI Approved :: MIT License
Classifier: Operating System :: OS Independent
Requires-Dist: bonelate
